django_rest_fast/__init__.py
django_rest_fast/apps.py
django_rest_fast/conf.py
django_rest_fast/decorators.py
django_rest_fast/format.py
django_rest_fast/forms.py
django_rest_fast/paths.py
django_rest_fast/schema.py
django_rest_fast/tests.py
django_rest_fast/urls.py
django_rest_fast/utils.py
django_rest_fast/views.py
django_rest_fast-0.0.3.dist-info/LICENSE.txt
django_rest_fast-0.0.3.dist-info/METADATA
django_rest_fast-0.0.3.dist-info/WHEEL
django_rest_fast-0.0.3.dist-info/top_level.txt
django_rest_fast-0.0.3.dist-info/RECORD
